enamlnative_charts.py
enaml_native_charts-1.0.3.data/data/packages/enaml-native-charts/android/.gitignore
enaml_native_charts-1.0.3.data/data/packages/enaml-native-charts/android/android.iml
enaml_native_charts-1.0.3.data/data/packages/enaml-native-charts/android/build.gradle
enaml_native_charts-1.0.3.data/data/packages/enaml-native-charts/android/gradlew
enaml_native_charts-1.0.3.data/data/packages/enaml-native-charts/android/gradlew.bat
enaml_native_charts-1.0.3.data/data/packages/enaml-native-charts/android/local.properties
enaml_native_charts-1.0.3.data/data/packages/enaml-native-charts/android/proguard-rules.pro
enaml_native_charts-1.0.3.data/data/packages/enaml-native-charts/android/gradle/wrapper/gradle-wrapper.jar
enaml_native_charts-1.0.3.data/data/packages/enaml-native-charts/android/gradle/wrapper/gradle-wrapper.properties
enaml_native_charts-1.0.3.data/data/packages/enaml-native-charts/android/src/main/AndroidManifest.xml
enaml_native_charts-1.0.3.data/data/packages/enaml-native-charts/android/src/main/java/com/codelv/enamlnative/packages/ChartsPackage.java
enaml_native_charts-1.0.3.data/data/packages/enaml-native-charts/ios/recipes/README.md
enaml_native_charts-1.0.3.data/data/packages/enaml-native-charts/src/setup.py
enaml_native_charts-1.0.3.data/data/packages/enaml-native-charts/src/charts/__init__.py
enaml_native_charts-1.0.3.data/data/packages/enaml-native-charts/src/charts/android/__init__.py
enaml_native_charts-1.0.3.data/data/packages/enaml-native-charts/src/charts/android/android_chart_view.py
enaml_native_charts-1.0.3.data/data/packages/enaml-native-charts/src/charts/android/factories.py
enaml_native_charts-1.0.3.data/data/packages/enaml-native-charts/src/charts/widgets/__init__.py
enaml_native_charts-1.0.3.data/data/packages/enaml-native-charts/src/charts/widgets/api.py
enaml_native_charts-1.0.3.data/data/packages/enaml-native-charts/src/charts/widgets/chart_view.py
enaml_native_charts-1.0.3.dist-info/DESCRIPTION.rst
enaml_native_charts-1.0.3.dist-info/METADATA
enaml_native_charts-1.0.3.dist-info/RECORD
enaml_native_charts-1.0.3.dist-info/WHEEL
enaml_native_charts-1.0.3.dist-info/entry_points.txt
enaml_native_charts-1.0.3.dist-info/metadata.json
enaml_native_charts-1.0.3.dist-info/top_level.txt
