Metadata-Version: 2.0
Name: enaml-native-charts
Version: 1.0.3
Summary: enaml-native-charts package for enaml-native-cli
Home-page: UNKNOWN
Author: jrm
Author-email: UNKNOWN
License: MIT
Platform: UNKNOWN
Requires-Dist: enaml-native (>=3.0.0)
